AUTHORS.rst
CHANGES.rst
CONTRIBUTE.rst
MANIFEST.in
README.rst
TODO.rst
runtests.py
setup.cfg
setup.py
django_record/__init__.py
django_record/mixins.py
django_record/models.py
django_record/querysets.py
django_record/utils.py
django_record.egg-info/PKG-INFO
django_record.egg-info/SOURCES.txt
django_record.egg-info/dependency_links.txt
django_record.egg-info/requires.txt
django_record.egg-info/top_level.txt