Metadata-Version: 1.1
Name: django-record
Version: 0.2.5
Summary: Models and mixins for recording changes in Django models
Home-page: https://github.com/kuc2477/django-record/
Author: Ha Junsoo
Author-email: kuc2477@gmail.com
License: GNU General Public License v2 (GPLv2)
Platform: OS Independent
Classifier: Development Status :: 3 - Alpha
Classifier: Environment :: Web Environment
Classifier: Intended Audience :: Developers
Classifier: License :: OSI Approved :: GNU General Public License v2 (GPLv2)
Classifier: Operating System :: OS Independent
Classifier: Programming Language :: Python
Classifier: Programming Language :: Python :: 2.7
Classifier: Programming Language :: Python :: 3.4
Classifier: Framework :: Django
